incompatible_library/__init__.py
incompatible_library/math_funcs.py
incompatible_library-2.0.0.dist-info/WHEEL
incompatible_library-2.0.0.dist-info/METADATA
incompatible_library-2.0.0.dist-info/RECORD
